Metadata-Version: 2.4
Name: seclab-research-depconf-test
Version: 1.1
Summary: blah
Author-email: Your Name <your@email.com>
License: MIT
Keywords: example
Classifier: Programming Language :: Python :: 3
Classifier: License :: OSI Approved :: MIT License
Classifier: Operating System :: OS Independent
Requires-Python: >=3.5
